pybuffer/__init__.py
pybuffer-0.2.0.dist-info/DESCRIPTION.rst
pybuffer-0.2.0.dist-info/METADATA
pybuffer-0.2.0.dist-info/RECORD
pybuffer-0.2.0.dist-info/WHEEL
pybuffer-0.2.0.dist-info/metadata.json
pybuffer-0.2.0.dist-info/top_level.txt
