Metadata-Version: 2.0
Name: pybuffer
Version: 0.2.0
Summary: pybuffer utility for ctypes
Home-page: https://github.com/ShigekiKarita/mir-pybuffer
Author: Shigeki Karita
Author-email: shigekikarita@gmail.com
License: BSL-1.0
Keywords: ctypes
Platform: UNKNOWN
Classifier: Programming Language :: Python :: 3
